device_resolutions/__init__.py
device_resolutions-0.0.2.dist-info/DESCRIPTION.rst
device_resolutions-0.0.2.dist-info/METADATA
device_resolutions-0.0.2.dist-info/RECORD
device_resolutions-0.0.2.dist-info/WHEEL
device_resolutions-0.0.2.dist-info/entry_points.txt
device_resolutions-0.0.2.dist-info/metadata.json
device_resolutions-0.0.2.dist-info/top_level.txt
