Metadata-Version: 2.0
Name: device-resolutions
Version: 0.0.2
Summary: A large collection of device resolution information
Home-page: https://github.com/gordonbrander/device_resolutions
Author: Gordon Brander
Author-email: UNKNOWN
License: MIT
Platform: UNKNOWN
Classifier: Development Status :: 3 - Alpha
Classifier: Intended Audience :: Developers
Classifier: Programming Language :: Python :: 2.7
